lion_core/__init__.py
lion_core/_class_registry.py
lion_core/abc/__init__.py
lion_core/abc/characteristic.py
lion_core/abc/concept.py
lion_core/abc/observation.py
lion_core/abc/observer.py
lion_core/abc/record.py
lion_core/abc/space.py
lion_core/action/__init__.py
lion_core/action/action_executor.py
lion_core/action/action_processor.py
lion_core/action/base.py
lion_core/action/function_calling.py
lion_core/action/tool.py
lion_core/action/tool_manager.py
lion_core/communication/__init__.py
lion_core/communication/action_request.py
lion_core/communication/action_response.py
lion_core/communication/assistant_response.py
lion_core/communication/base_mail.py
lion_core/communication/instruction.py
lion_core/communication/mail.py
lion_core/communication/mail_manager.py
lion_core/communication/message.py
lion_core/communication/message_manager.py
lion_core/communication/package.py
lion_core/communication/start_mail.py
lion_core/communication/system.py
lion_core/communication/utils.py
lion_core/exceptions.py
lion_core/form/__init__.py
lion_core/form/base.py
lion_core/form/form.py
lion_core/form/report.py
lion_core/form/utils.py
lion_core/generic/__init__.py
lion_core/generic/component.py
lion_core/generic/element.py
lion_core/generic/exchange.py
lion_core/generic/flow.py
lion_core/generic/log.py
lion_core/generic/log_manager.py
lion_core/generic/node.py
lion_core/generic/pile.py
lion_core/generic/progression.py
lion_core/generic/utils.py
lion_core/graph/__init__.py
lion_core/graph/edge.py
lion_core/graph/edge_condition.py
lion_core/graph/graph.py
lion_core/integrations/__init__.py
lion_core/integrations/pandas_/__init__.py
lion_core/integrations/pandas_/extend_df.py
lion_core/integrations/pandas_/read.py
lion_core/integrations/pandas_/remove_rows.py
lion_core/integrations/pandas_/replace_keywords.py
lion_core/integrations/pandas_/save.py
lion_core/integrations/pandas_/search_keywords.py
lion_core/integrations/pandas_/to_df.py
lion_core/integrations/pandas_/update_cells.py
lion_core-1.2.3.dist-info/LICENSE
lion_core-1.2.3.dist-info/METADATA
lion_core-1.2.3.dist-info/WHEEL
lion_core-1.2.3.dist-info/RECORD
