Metadata-Version: 2.1
Name: lion-core
Version: 1.2.3
Summary: A core package for the Lion framework.
Author: HaiyangLi
Author-email: quantocean.li@gmail.com
Requires-Python: >=3.11,<4.0
Classifier: Programming Language :: Python :: 3
Classifier: Programming Language :: Python :: 3.11
Classifier: Programming Language :: Python :: 3.12
Requires-Dist: lion-service (>=1.1.0,<2.0.0)
Requires-Dist: lionfuncs (>=2.0.0,<3.0.0)
